ncloud_clouddb/__init__.py
ncloud_clouddb/api_client.py
ncloud_clouddb/configuration.py
ncloud_clouddb/rest.py
ncloud_clouddb/api/__init__.py
ncloud_clouddb/api/v2_api.py
ncloud_clouddb/model/__init__.py
ncloud_clouddb/model/access_control_group.py
ncloud_clouddb/model/backup_file.py
ncloud_clouddb/model/cloud_db_config.py
ncloud_clouddb/model/cloud_db_config_group.py
ncloud_clouddb/model/cloud_db_instance.py
ncloud_clouddb/model/cloud_db_server_instance.py
ncloud_clouddb/model/common_code.py
ncloud_clouddb/model/create_cloud_db_instance_request.py
ncloud_clouddb/model/create_cloud_db_instance_response.py
ncloud_clouddb/model/delete_cloud_db_server_instance_request.py
ncloud_clouddb/model/delete_cloud_db_server_instance_response.py
ncloud_clouddb/model/dms_file.py
ncloud_clouddb/model/download_dms_file_request.py
ncloud_clouddb/model/download_dms_file_response.py
ncloud_clouddb/model/flush_cloud_db_instance_request.py
ncloud_clouddb/model/flush_cloud_db_instance_response.py
ncloud_clouddb/model/get_backup_list_request.py
ncloud_clouddb/model/get_backup_list_response.py
ncloud_clouddb/model/get_cloud_db_config_group_list_request.py
ncloud_clouddb/model/get_cloud_db_config_group_list_response.py
ncloud_clouddb/model/get_cloud_db_image_product_list_request.py
ncloud_clouddb/model/get_cloud_db_image_product_list_response.py
ncloud_clouddb/model/get_cloud_db_instance_list_request.py
ncloud_clouddb/model/get_cloud_db_instance_list_response.py
ncloud_clouddb/model/get_cloud_db_product_list_request.py
ncloud_clouddb/model/get_cloud_db_product_list_response.py
ncloud_clouddb/model/get_dms_operation_request.py
ncloud_clouddb/model/get_dms_operation_response.py
ncloud_clouddb/model/get_object_storage_backup_list_request.py
ncloud_clouddb/model/get_object_storage_backup_list_response.py
ncloud_clouddb/model/product.py
ncloud_clouddb/model/reboot_cloud_db_server_instance_request.py
ncloud_clouddb/model/reboot_cloud_db_server_instance_response.py
ncloud_clouddb/model/region.py
ncloud_clouddb-1.1.1.dist-info/LICENSE
ncloud_clouddb-1.1.1.dist-info/METADATA
ncloud_clouddb-1.1.1.dist-info/WHEEL
ncloud_clouddb-1.1.1.dist-info/top_level.txt
ncloud_clouddb-1.1.1.dist-info/RECORD
