Metadata-Version: 1.0
Name: ncloud-clouddb
Version: 1.1.1
Summary: clouddb
Home-page: UNKNOWN
Author: UNKNOWN
Author-email: UNKNOWN
License: UNKNOWN
Keywords: clouddb
Platform: UNKNOWN
